README.txt
TODO.txt
bootstrap.py
buildout.cfg
devel.cfg
ignores.txt
setup.cfg
setup.py
docs/HISTORY.txt
docs/INSTALL.txt
docs/LICENSE.txt
src/ely/__init__.py
src/ely.contentgenerator.egg-info/PKG-INFO
src/ely.contentgenerator.egg-info/SOURCES.txt
src/ely.contentgenerator.egg-info/dependency_links.txt
src/ely.contentgenerator.egg-info/namespace_packages.txt
src/ely.contentgenerator.egg-info/not-zip-safe
src/ely.contentgenerator.egg-info/requires.txt
src/ely.contentgenerator.egg-info/top_level.txt
src/ely/contentgenerator/README.txt
src/ely/contentgenerator/__init__.py
src/ely/contentgenerator/configure.zcml
src/ely/contentgenerator/contentgeneration.py
src/ely/contentgenerator/contentsniffer.py
src/ely/contentgenerator/interfaces.py
src/ely/contentgenerator/namespaces.py
src/ely/contentgenerator/tests/__init__.py
src/ely/contentgenerator/tests/page4_description.txt
src/ely/contentgenerator/tests/samplecontent2.xml
src/ely/contentgenerator/tests/testcontent1.txt
src/ely/contentgenerator/tests/tests.py
src/ely/contentgenerator/tests/users.py