Metadata-Version: 1.0
Name: ely.contentgenerator
Version: 0.1.dev-r149
Summary: Product for creating content in Zope
Home-page: http://ely.googlecode.com/svn/ely.contentgenerator/trunk
Author: Matt Halstead
Author-email: matt@elyt.com
License: new BSD
Platform: UNKNOWN
